{
    "IsRiderSecondaryApplicationRunningPermissionGrantable": true,
    "IsWebstormSecondaryClientappRunningPermissionGrantable": false,
    "IsOpeningFeatureSelfAddress": true,
    "IsOpeningAutomationsDirectory": true,
    "IsOpeningCommandsDirectory": true,
    "IsOpeningEnvironmentVariablesFilesDirectory": true,
    "IsOpeningOperationsDirectory": true,
    "IsOpeningDataDirectory": true,
    "IsOpeningFendAddress": true,
    "IsOpeningFendPrimaryAddress": true,
    "IsOpeningFendSecondaryAddress": true,
    "IsOpeningBendAddress": true,
    "IsOpeningBendPrimaryAddress": true,
    "IsOpeningBendSecondaryAddress": true,
    "IsOpeningCallsAddress": true,
    "IsOpeningToolsAddress": true,
    "IsOpeningNotesMessagesAddress": true,
    "IsOpeningWebLinksAddress": true,
    "PrimaryApplicationLocation": "C:\\workplace\\GitHub\\working-circulation\\dotnet\\Organumator\\organumator\\organumator.backend\\organumator.sln",
    "SecondaryApplicationLocation": "secondary/application/location",
    "SecondaryApplicationProjectLocation": "secondary/application/project/location",
    "SecondaryApplicationProjectName": "secondary/application/project/name",
    "PrimaryApplicationProjectLocation": "primary/application/project/location",
    "PrimaryApplicationProjectName": "primary/application/project/name",
    "AllInclusiveDirectoryAddress": "all/inclusive/directory/address",
    "PrimaryClientappLocation":"C:\\workplace\\GitHub\\working-circulation\\dotnet\\Organumator\\organumator\\organumator.frontend",
    "SecondaryClientappLocation": "secondary/clientapp/location"
}
